joseki/__init__.py
joseki/__main__.py
joseki/__version__.py
joseki/accessor.py
joseki/constants.py
joseki/core.py
joseki/units.py
joseki/data/README.md
joseki/data/__init__.py
joseki/data/afgl_1986/README.md
joseki/data/afgl_1986/__init__.py
joseki/data/afgl_1986/table_1a.csv
joseki/data/afgl_1986/table_1b.csv
joseki/data/afgl_1986/table_1c.csv
joseki/data/afgl_1986/table_1d.csv
joseki/data/afgl_1986/table_1e.csv
joseki/data/afgl_1986/table_1f.csv
joseki/data/afgl_1986/table_2a.csv
joseki/data/afgl_1986/table_2b.csv
joseki/data/afgl_1986/table_2c.csv
joseki/data/afgl_1986/table_2d.csv
joseki/data/mipas_2007/README.md
joseki/data/mipas_2007/__init__.py
joseki/data/mipas_2007/extra.atm
joseki/data/mipas_2007/midlatitude_day.atm
joseki/data/mipas_2007/midlatitude_night.atm
joseki/data/mipas_2007/polar_summer.atm
joseki/data/mipas_2007/polar_winter.atm
joseki/data/mipas_2007/tropical.atm
joseki/profiles/__init__.py
joseki/profiles/afgl_1986.py
joseki/profiles/core.py
joseki/profiles/factory.py
joseki/profiles/mipas_2007.py
joseki/profiles/schema.py
joseki/profiles/ussa_1976.py
joseki/profiles/util.py
joseki-2.6.1.dist-info/METADATA
joseki-2.6.1.dist-info/WHEEL
joseki-2.6.1.dist-info/entry_points.txt
joseki-2.6.1.dist-info/licenses/LICENSE
joseki-2.6.1.dist-info/RECORD
