Metadata-Version: 2.1
Name: joseki
Version: 2.6.1
Summary: Reference atmospheric thermophysical profiles for radiative transfer applications in Earth's atmosphere.
Project-URL: changelog, https://github.com/rayference/joseki/blob/main/docs/changelog.md
Project-URL: documentation, https://rayference.github.io/joseki/latest
Project-URL: homepage, https://github.com/rayference/joseki
Project-URL: issues, https://github.com/rayference/joseki/issues
Project-URL: repository, https://github.com/rayference/joseki
Author-email: Yvan Nollet <yvan.nollet@rayference.eu>, Vincent Leroy <vincent.leroy@rayference.eu>
License: LGPLv3
License-File: LICENSE
Classifier: Programming Language :: Python :: 3.8
Classifier: Programming Language :: Python :: 3.9
Classifier: Programming Language :: Python :: 3.10
Classifier: Programming Language :: Python :: 3.11
Classifier: Programming Language :: Python :: 3.12
Requires-Python: >=3.9
Requires-Dist: attrs>=22.2.0
Requires-Dist: click>=8.1.3
Requires-Dist: importlib-resources>=5.10.2
Requires-Dist: netcdf4>=1.6.2
Requires-Dist: numpy>=1.22.0
Requires-Dist: pandas>=1.5.2
Requires-Dist: pint>=0.20.1
Requires-Dist: scipy>=1.9.3
Requires-Dist: ussa1976>=0.3.4
Requires-Dist: xarray>=2022.12.0
